KekikStream/__init__.py
KekikStream/__main__.py
KekikStream/requirements.txt
KekikStream/CLI/__init__.py
KekikStream/CLI/pypi_kontrol.py
KekikStream/Core/HTMLHelper.py
KekikStream/Core/__init__.py
KekikStream/Core/Extractor/ExtractorBase.py
KekikStream/Core/Extractor/ExtractorLoader.py
KekikStream/Core/Extractor/ExtractorManager.py
KekikStream/Core/Extractor/ExtractorModels.py
KekikStream/Core/Extractor/YTDLPCache.py
KekikStream/Core/Media/MediaHandler.py
KekikStream/Core/Media/MediaManager.py
KekikStream/Core/Plugin/PluginBase.py
KekikStream/Core/Plugin/PluginLoader.py
KekikStream/Core/Plugin/PluginManager.py
KekikStream/Core/Plugin/PluginModels.py
KekikStream/Core/UI/UIManager.py
KekikStream/Extractors/Abstream.py
KekikStream/Extractors/CloseLoad.py
KekikStream/Extractors/ContentX.py
KekikStream/Extractors/DonilasPlay.py
KekikStream/Extractors/DzenRu.py
KekikStream/Extractors/ExPlay.py
KekikStream/Extractors/Filemoon.py
KekikStream/Extractors/HDMomPlayer.py
KekikStream/Extractors/HDPlayerSystem.py
KekikStream/Extractors/HotStream.py
KekikStream/Extractors/JFVid.py
KekikStream/Extractors/JetTv.py
KekikStream/Extractors/JetV.py
KekikStream/Extractors/MailRu.py
KekikStream/Extractors/MixPlayHD.py
KekikStream/Extractors/MixTiger.py
KekikStream/Extractors/MolyStream.py
KekikStream/Extractors/Odnoklassniki.py
KekikStream/Extractors/PeaceMakerst.py
KekikStream/Extractors/PixelDrain.py
KekikStream/Extractors/PlayerFilmIzle.py
KekikStream/Extractors/RapidVid.py
KekikStream/Extractors/SetPlay.py
KekikStream/Extractors/SetPrime.py
KekikStream/Extractors/SibNet.py
KekikStream/Extractors/Sobreatsesuyp.py
KekikStream/Extractors/TRsTX.py
KekikStream/Extractors/TauVideo.py
KekikStream/Extractors/TurboImgz.py
KekikStream/Extractors/TurkeyPlayer.py
KekikStream/Extractors/VCTPlay.py
KekikStream/Extractors/Veev.py
KekikStream/Extractors/VidBiz.py
KekikStream/Extractors/VidHide.py
KekikStream/Extractors/VidMoly.py
KekikStream/Extractors/VidMoxy.py
KekikStream/Extractors/VidPapi.py
kekikstream-2.5.6.dist-info/licenses/LICENSE
kekikstream-2.5.6.dist-info/METADATA
kekikstream-2.5.6.dist-info/WHEEL
kekikstream-2.5.6.dist-info/entry_points.txt
kekikstream-2.5.6.dist-info/top_level.txt
kekikstream-2.5.6.dist-info/RECORD
