Metadata-Version: 2.4
Name: KekikStream
Version: 2.5.6
Summary: terminal üzerinden medya içeriği aramanızı ve VLC/MPV gibi popüler medya oynatıcılar aracılığıyla doğrudan izlemenizi sağlayan modüler ve genişletilebilir bir bıdı bıdı
Home-page: https://github.com/keyiflerolsun/KekikStream
Author: keyiflerolsun
Author-email: keyiflerolsun@gmail.com
License: GPLv3+
Keywords: KekikStream,KekikAkademi,keyiflerolsun
Classifier: Development Status :: 5 - Production/Stable
Classifier: License :: OSI Approved :: GNU General Public License v3 or later (GPLv3+)
Classifier: Programming Language :: Python :: 3
Requires-Python: >=3.11
License-File: LICENSE
Requires-Dist: setuptools
Requires-Dist: wheel
Requires-Dist: Kekik>=1.9.5
Requires-Dist: httpx
Requires-Dist: cloudscraper
Requires-Dist: selectolax
Requires-Dist: pydantic
Requires-Dist: InquirerPy
Requires-Dist: yt-dlp
Dynamic: author
Dynamic: author-email
Dynamic: classifier
Dynamic: description
Dynamic: description-content-type
Dynamic: home-page
Dynamic: keywords
Dynamic: license
Dynamic: license-file
Dynamic: requires-dist
Dynamic: requires-python
Dynamic: summary
